im_gcsfilesharded/__init__.py
im_gcsfilesharded-0.1.0.dist-info/DESCRIPTION.rst
im_gcsfilesharded-0.1.0.dist-info/METADATA
im_gcsfilesharded-0.1.0.dist-info/RECORD
im_gcsfilesharded-0.1.0.dist-info/WHEEL
im_gcsfilesharded-0.1.0.dist-info/metadata.json
im_gcsfilesharded-0.1.0.dist-info/top_level.txt
